odoo/addons/product_pricelist_direct_print_website_sale/README.rst
odoo/addons/product_pricelist_direct_print_website_sale/__init__.py
odoo/addons/product_pricelist_direct_print_website_sale/__manifest__.py
odoo/addons/product_pricelist_direct_print_website_sale/i18n/es.po
odoo/addons/product_pricelist_direct_print_website_sale/i18n/it.po
odoo/addons/product_pricelist_direct_print_website_sale/i18n/product_pricelist_direct_print_website_sale.pot
odoo/addons/product_pricelist_direct_print_website_sale/i18n/product_pricelist_print_website_sale.pot
odoo/addons/product_pricelist_direct_print_website_sale/i18n/tr.po
odoo/addons/product_pricelist_direct_print_website_sale/readme/CONTRIBUTORS.md
odoo/addons/product_pricelist_direct_print_website_sale/readme/DESCRIPTION.md
odoo/addons/product_pricelist_direct_print_website_sale/readme/USAGE.md
odoo/addons/product_pricelist_direct_print_website_sale/report/__init__.py
odoo/addons/product_pricelist_direct_print_website_sale/report/product_pricelist_xlsx.py
odoo/addons/product_pricelist_direct_print_website_sale/static/description/icon.png
odoo/addons/product_pricelist_direct_print_website_sale/static/description/index.html
odoo/addons/product_pricelist_direct_print_website_sale/wizards/__init__.py
odoo/addons/product_pricelist_direct_print_website_sale/wizards/product_pricelist_print.py
odoo/addons/product_pricelist_direct_print_website_sale/wizards/product_pricelist_print_view.xml
odoo_addon_product_pricelist_direct_print_website_sale-18.0.1.0.0.3.dist-info/METADATA
odoo_addon_product_pricelist_direct_print_website_sale-18.0.1.0.0.3.dist-info/WHEEL
odoo_addon_product_pricelist_direct_print_website_sale-18.0.1.0.0.3.dist-info/top_level.txt
odoo_addon_product_pricelist_direct_print_website_sale-18.0.1.0.0.3.dist-info/RECORD
